mlops/__init__.py
mlops/config.py
mlops/dataset.py
mlops/predict.py
mlops/train.py
mlops_fropych-0.0.1.dist-info/METADATA
mlops_fropych-0.0.1.dist-info/WHEEL
mlops_fropych-0.0.1.dist-info/top_level.txt
mlops_fropych-0.0.1.dist-info/RECORD
