Metadata-Version: 2.1
Name: mlops-fropych
Version: 0.0.1
Summary: A short description of the project.
Author: Yaroslav
Classifier: Programming Language :: Python :: 3
Requires-Python: ~=3.10
